CHANGES.txt
LICENSE.txt
MANIFEST.in
README.txt
setup.py
FS_Hopper.egg-info/PKG-INFO
FS_Hopper.egg-info/SOURCES.txt
FS_Hopper.egg-info/dependency_links.txt
FS_Hopper.egg-info/requires.txt
FS_Hopper.egg-info/top_level.txt
fs_hopper/__init__.py
fs_hopper/nodes.py