Metadata-Version: 1.0
Name: FS-Hopper
Version: 0.1.0
Summary: Simple object-oriented access to a filesystem directory tree
Home-page: http://pypi.python.org/pypi/FS-Hopper/
Author: Brian Wiborg
Author-email: baccenfutter@c-base.org
License: LICENSE.txt
Platform: UNKNOWN
